gupao/__init__.py
gupao/apis.py
gupao/gu.py
gupao/models.py
gupao-0.0.6.dist-info/METADATA
gupao-0.0.6.dist-info/WHEEL
gupao-0.0.6.dist-info/top_level.txt
gupao-0.0.6.dist-info/RECORD
