Metadata-Version: 2.1
Name: gupao
Version: 0.0.6
Summary: 咕泡云课堂接口
Author-email: cquestor <jishi2206@gmail.com>
Requires-Python: >=3.8
Requires-Dist: requests
